src/ImmGen.vhd
library IEEE;
use IEEE.STD_LOGIC_1164.ALL;
use IEEE.NUMERIC_STD.ALL;

entity ImmGen is
    Port (
        instr    : in  STD_LOGIC_VECTOR (31 downto 0);
        imm_out  : out STD_LOGIC_VECTOR (31 downto 0) 
    );
end ImmGen;

architecture Behavioral of ImmGen is
    signal imm_i  : STD_LOGIC_VECTOR(31 downto 0);  -- Inst Inmediatas
    signal imm_s  : STD_LOGIC_VECTOR(31 downto 0);  -- Inst Store
    signal imm_b  : STD_LOGIC_VECTOR(31 downto 0);  -- Inst Branch
    signal imm12  : STD_LOGIC_VECTOR(11 downto 0);  -- Inst Branch
    signal sel    : STD_LOGIC_VECTOR(1 downto 0);

begin
    -- Extraer el selector de opcode (bits 6 y 5) los bits más significativos
    -- del opcode determinan el formato de instruccion
    sel <= instr(6 downto 5);

    -- Replicar el bit mas significativo 31

    -- I-Type (Load)
    imm_i <= (31 downto 12 => instr(31)) & instr(31 downto 20);  

    -- S-Type (Store)
    imm_s <= (31 downto 12 => instr(31)) & instr(31 downto 25) & instr(11 downto 7); 

    -- B-Type (Branch)
    imm_b <= (31 downto 12 => instr(31)) & instr(7) & instr(30 downto 25) & instr(11 downto 8) & '0';

    -- Multiplexor para seleccionar el inmediato correcto
    with sel select 
        imm_out <= imm_i when "00",  -- Load (I-Type)
                   imm_s when "01",  -- Store (S-Type)
                   imm_b when "10",  -- Branch (B-Type)
                   imm_b when "11",  -- Branch
                   (others => '0') when others; -- Default (0)

end Behavioral;

tb/tb_ImmGen.vhd
library IEEE;
use IEEE.STD_LOGIC_1164.ALL;
use IEEE.NUMERIC_STD.ALL;

entity tb_ImmGen is
end tb_ImmGen;

architecture testbench of tb_ImmGen is
    -- Señales del testbench
    signal instr   : STD_LOGIC_VECTOR (31 downto 0) := (others => '0');
    signal imm_out : STD_LOGIC_VECTOR (31 downto 0);
    
    -- Componente a probar (DUT - Device Under Test)
    component ImmGen
        Port (
            instr  : in  STD_LOGIC_VECTOR (31 downto 0);
            imm_out: out STD_LOGIC_VECTOR (31 downto 0)
        );
    end component;

begin
    -- Instancia del DUT
    UUT: ImmGen port map (
        instr  => instr,
        imm_out => imm_out
    );

    -- Proceso de simulación
    process
    begin
        -- LW x0, 4(x0)
        -- Carga el valor de memoria desde la dirección x0 + 4 en el registro x0.
        -- valor esperado: 0x00000004
        instr <= X"00402003";
        wait for 10 ns;

        -- SW x0, 4(x1)
        -- Almacena el valor de x0 en memoria en la dirección x1 + 4.
        -- valor esperado: 0x00000004
        instr <= X"00402003";
        wait for 10 ns;

        -- BEQ x1, x2, -4
        -- Salta a la dirección actual - 4 si los valores de x1 y x2 son iguales.
        -- valor esperado: 0xFFFFFFFC
        instr <= X"fe208ee3";
        wait for 10 ns;

        -- ADDI x3, x4, 10
        -- Suma el valor inmediato 10 al contenido de x4 y guarda el resultado en x3.
        -- valor esperado: 0x0000000A
        instr <= X"00a20193";
        wait for 10 ns;

        -- SW x5, 20(x6)
        -- Almacena el valor de x5 en memoria en la dirección x6 + 20.
        -- valor esperado: 	0x00000014
        instr <= X"00532a23";
        wait for 10 ns;

        -- BNE x7, x8, 16
        -- Salta a la dirección actual + 16 si los valores de x7 y x8 son diferentes.
        -- valor esperado: 0x00000010
        instr <= X"00839863";
        wait for 10 ns;

        -- ORI x9, x10, 255
        -- Realiza una operación OR entre x10 y el inmediato 255, y guarda el resultado en x9.
        -- valor esperado: 0x000000FF
        instr <= X"0ff56493";
        wait for 10 ns;

        -- ADDI x5, x6, -16
        -- Suma el valor inmediato -16 (12 bits extendido) al registro x6 y coloca el resultado en x5.
        -- valor esperado: 0xFFFFFFF0
        instr <= X"ff030293";
        wait for 10 ns;

        -- SW x7, -8(x8)
        -- Almacena el valor de x7 en la memoria en la dirección x8 + (-8) (inmediato extendido).
        -- valor esperado: 0xFFFFFFF8
        instr <= X"fe742c23";
        wait for 10 ns;

        -- BEQ x10, x11, 4
        -- Salta a la dirección 4 si los valores de x10 y x11 son iguales. Inmediato de 12 bits extendido.
        -- valor esperado: 0x00000004
        instr <= X"00b50263";
        wait for 10 ns;

        instr <= X"00000000";
        wait for 40 ns;


    end process;

end testbench;

sim/tb_ImmGen/wave.vcd
$date
  Mon Mar  3 22:04:36 2025
$end
$version
  GHDL v0
$end
$timescale
  1 fs
$end
$scope module standard $end
$upscope $end
$scope module textio $end
$upscope $end
$scope module std_logic_1164 $end
$upscope $end
$scope module numeric_std $end
$upscope $end
$scope module tb_immgen $end
$var reg 32 ! instr[31:0] $end
$var reg 32 " imm_out[31:0] $end
$scope module uut $end
$var reg 32 # instr[31:0] $end
$var reg 32 $ imm_out[31:0] $end
$var reg 32 % imm_i[31:0] $end
$var reg 32 & imm_s[31:0] $end
$var reg 32 ' imm_b[31:0] $end
$var reg 12 ( imm12[11:0] $end
$var reg 2 ) sel[1:0] $end
$upscope $end
$upscope $end
$enddefinitions $end
#0
b00000000010000000010000000000011 !
b00000000000000000000000000000100 "
b00000000010000000010000000000011 #
b00000000000000000000000000000100 $
b00000000000000000000000000000100 %
b00000000000000000000000000000000 &
b00000000000000000000000000000000 '
bUUUUUUUUUUUU (
b00 )
#10000000
#20000000
b11111110001000001000111011100011 !
b11111111111111111111111111111100 "
b11111110001000001000111011100011 #
b11111111111111111111111111111100 $
b11111111111111111111111111100010 %
b11111111111111111111111111111101 &
b11111111111111111111111111111100 '
b11 )
#30000000
b00000000101000100000000110010011 !
b00000000000000000000000000001010 "
b00000000101000100000000110010011 #
b00000000000000000000000000001010 $
b00000000000000000000000000001010 %
b00000000000000000000000000000011 &
b00000000000000000000100000000010 '
b00 )
#40000000
b00000000010100110010101000100011 !
b00000000000000000000000000010100 "
b00000000010100110010101000100011 #
b00000000000000000000000000010100 $
b00000000000000000000000000000101 %
b00000000000000000000000000010100 &
b00000000000000000000000000010100 '
b01 )
#50000000
b00000000100000111001100001100011 !
b00000000000000000000000000010000 "
b00000000100000111001100001100011 #
b00000000000000000000000000010000 $
b00000000000000000000000000001000 %
b00000000000000000000000000010000 &
b00000000000000000000000000010000 '
b11 )
#60000000
b00001111111101010110010010010011 !
b00000000000000000000000011111111 "
b00001111111101010110010010010011 #
b00000000000000000000000011111111 $
b00000000000000000000000011111111 %
b00000000000000000000000011101001 &
b00000000000000000000100011101000 '
b00 )
#70000000
b11111111000000110000001010010011 !
b11111111111111111111111111110000 "
b11111111000000110000001010010011 #
b11111111111111111111111111110000 $
b11111111111111111111111111110000 %
b11111111111111111111111111100101 &
b11111111111111111111111111100100 '
#80000000
b11111110011101000010110000100011 !
b11111111111111111111111111111000 "
b11111110011101000010110000100011 #
b11111111111111111111111111111000 $
b11111111111111111111111111100111 %
b11111111111111111111111111111000 &
b11111111111111111111011111111000 '
b01 )
#90000000
b00000000101101010000001001100011 !
b00000000000000000000000000000100 "
b00000000101101010000001001100011 #
b00000000000000000000000000000100 $
b00000000000000000000000000001011 %
b00000000000000000000000000000100 &
b00000000000000000000000000000100 '
b11 )
#100000000
b00000000000000000000000000000000 !
b00000000000000000000000000000000 "
b00000000000000000000000000000000 #
b00000000000000000000000000000000 $
b00000000000000000000000000000000 %
b00000000000000000000000000000000 &
b00000000000000000000000000000000 '
b00 )
#140000000
b00000000010000000010000000000011 !
b00000000000000000000000000000100 "
b00000000010000000010000000000011 #
b00000000000000000000000000000100 $
b00000000000000000000000000000100 %
