src/RAM.vhd

library IEEE;
use IEEE.STD_LOGIC_1164.ALL;
use IEEE.NUMERIC_STD.ALL;

entity RAM is
    Port (
        clk      : in  STD_LOGIC;
        reset    : in  STD_LOGIC;  
        we       : in  STD_LOGIC;  
        re       : in  STD_LOGIC;  
        addr     : in  STD_LOGIC_VECTOR(31 downto 0); -- Byte address
        din      : in  STD_LOGIC_VECTOR(31 downto 0); -- Data input (for store)
        funct3   : in  STD_LOGIC_VECTOR(2 downto 0);  -- Selects lw, lh, lb, sw, sh, sb
        dout     : out STD_LOGIC_VECTOR(31 downto 0)  -- Data output (for load)
    );
end RAM;

architecture Behavioral of RAM is
    type RAM_TYPE is array (0 to 1023) of STD_LOGIC_VECTOR(7 downto 0); -- 4 KB de RAM (1024 bytes)
    signal memory : RAM_TYPE := (others => (others => '0')); -- Inicializa en 0
    signal aligned_addr : INTEGER range 0 to 1023; -- Dirección truncada a 10 bits para el tamaño de la memoria
    signal dout_aux     :  STD_LOGIC_VECTOR(31 downto 0) := (others =>'0'); 

begin
    -- Convertir la dirección de bytes en un índice para la memoria
    aligned_addr <= to_integer(unsigned(addr(9 downto 0)));  -- Utilizamos solo los bits bajos para el índice
    
    -- Escritura de la memoria
    process(clk)
    begin
        if rising_edge(clk) then
            if reset = '1' then
                -- Resetear toda la memoria
                memory <= (others => (others => '0'));  
            elsif we = '1' then  -- Escritura
                case funct3 is
                    when "010" => -- sw (Store Word)
                        memory(aligned_addr)     <= din(7 downto 0);
                        memory(aligned_addr+1)   <= din(15 downto 8);
                        memory(aligned_addr+2)   <= din(23 downto 16);
                        memory(aligned_addr+3)   <= din(31 downto 24);
                    when "001" => -- sh (Store Halfword)
                        memory(aligned_addr)     <= din(7 downto 0);
                        memory(aligned_addr+1)   <= din(15 downto 8);
                    when "000" => -- sb (Store Byte)
                        memory(aligned_addr)     <= din(7 downto 0);
                    when others => 
                        null; -- No hacer nada para otras instrucciones
                end case;
            end if;
        end if;
    end process;

    -- Lectura de la memoria con signo extendido según el tipo de instrucción
    process(aligned_addr, funct3, re)
    begin
        case funct3 is
            when "010" => -- lw (Load Word)
                dout_aux <= memory(aligned_addr+3) & memory(aligned_addr+2) & memory(aligned_addr+1) & memory(aligned_addr);
            when "001" | "101" => -- lh / lhu (Load Halfword)
                -- Extensión de signo de 16 bits
                dout_aux(15 downto 0) <= memory(aligned_addr+1) & memory(aligned_addr);  -- Lee 2 bytes
                
                if funct3 = "001" then
                    dout_aux(31 downto 16) <= (others => dout_aux(15)); -- Extiende el bit más significativo a 16 bits
                else
                    dout_aux(31 downto 16) <= (others => '0'); -- Extiende el bit más significativo a 16 bits
                end if;

            when "000" | "100" => -- lb / lbu (Load Byte)
                -- Extensión de signo de 8 bits
                dout_aux(7 downto 0) <= memory(aligned_addr);   -- Lee 1 byte
                if funct3 = "000" then
                    dout_aux(31 downto 8) <= (others => dout_aux(7));   -- Extiende el bit más significativo a 24 bits
                else
                    dout_aux(31 downto 8) <= (others => '0');   -- Extiende el bit más significativo a 24 bits
                end if;
            when others => 
                dout_aux <= (others => '0'); -- Para cualquier otro caso
        end case;
    end process;
    
dout <= dout_aux when re ='1' else (others =>'0');

end Behavioral;

src/Cache.vhd
library IEEE;
use IEEE.STD_LOGIC_1164.ALL;
use IEEE.NUMERIC_STD.ALL;
use IEEE.MATH_REAL.ALL;

entity Cache is 
    generic (
        CACHE_SIZE : integer := 64  -- número de líneas de caché (potencia de 2)
    );
    Port (
        clk      : in  STD_LOGIC;
        reset    : in  STD_LOGIC;
        addr     : in  STD_LOGIC_VECTOR(31 downto 0);
        din      : in  STD_LOGIC_VECTOR(31 downto 0);
        we       : in  STD_LOGIC;
        re       : in  STD_LOGIC;
        funct3   : in  STD_LOGIC_VECTOR(2 downto 0);
        dout     : out STD_LOGIC_VECTOR(31 downto 0);
        miss     : out STD_LOGIC
    );
end Cache;


architecture Behavioral of Cache is

    constant INDEX_WIDTH  : integer := integer(ceil(log2(real(CACHE_SIZE))));
    constant OFFSET_WIDTH : integer := 2; -- palabra = 4 bytes
    constant TAG_WIDTH    : integer := 32 - INDEX_WIDTH - OFFSET_WIDTH;

    type cache_data_array is array (0 to CACHE_SIZE-1) of STD_LOGIC_VECTOR(31 downto 0);
    type tag_array        is array (0 to CACHE_SIZE-1) of STD_LOGIC_VECTOR(TAG_WIDTH-1 downto 0);
    type bit_array        is array (0 to CACHE_SIZE-1) of STD_LOGIC;

    signal data  : cache_data_array := (others => (others => '0'));
    signal tag   : tag_array        := (others => (others => '0'));
    signal valid : bit_array        := (others => '0');

    signal index       : integer range 0 to CACHE_SIZE-1;
    signal addr_tag    : STD_LOGIC_VECTOR(TAG_WIDTH-1 downto 0);
    signal hit         : STD_LOGIC;
    signal byte_offset : integer range 0 to 3;

    signal ram_re : STD_LOGIC := '0';
    signal ram_dout       : STD_LOGIC_VECTOR(31 downto 0) := (others => '0');
    signal ram_funct3   : STD_LOGIC_VECTOR(2 downto 0) := (others => '0');

    signal dout_comb : STD_LOGIC_VECTOR(31 downto 0) := (others => '0');
    -- signal dout_reg  : STD_LOGIC_VECTOR(31 downto 0) := (others => '0');

    signal miss_int  : STD_LOGIC := '0';
    signal ram_we : STD_LOGIC := '0';


    signal state : STD_LOGIC_VECTOR(1 downto 0) := "00";

    constant IDLE          : STD_LOGIC_VECTOR(1 downto 0) := "00";
    constant WAIT_READ     : STD_LOGIC_VECTOR(1 downto 0) := "01";
    constant WRITE_HB      : STD_LOGIC_VECTOR(1 downto 0) := "10";

    -- funct3 codes
    constant F3_BYTE    : STD_LOGIC_VECTOR(2 downto 0) := "000";
    constant F3_HALF    : STD_LOGIC_VECTOR(2 downto 0) := "001";
    constant F3_WORD    : STD_LOGIC_VECTOR(2 downto 0) := "010";
    constant F3_BYTE_U  : STD_LOGIC_VECTOR(2 downto 0) := "100";
    constant F3_HALF_U  : STD_LOGIC_VECTOR(2 downto 0) := "101";

    component RAM is
        Port (
            clk      : in  STD_LOGIC;
            reset    : in  STD_LOGIC;
            we       : in  STD_LOGIC;
            re       : in  STD_LOGIC;
            addr     : in  STD_LOGIC_VECTOR(31 downto 0);
            din      : in  STD_LOGIC_VECTOR(31 downto 0);
            funct3   : in  STD_LOGIC_VECTOR(2 downto 0);
            dout     : out STD_LOGIC_VECTOR(31 downto 0)
        );
    end component;

begin

    -- Address decoding
    index      <= to_integer(unsigned(addr(INDEX_WIDTH + OFFSET_WIDTH - 1 downto OFFSET_WIDTH)));
    addr_tag   <= addr(31 downto 32 - TAG_WIDTH);
    byte_offset <= to_integer(unsigned(addr(1 downto 0)));
    hit        <= '1' when valid(index) = '1' and tag(index) = addr_tag else '0';

    -- Miss flag combinacional
    miss_int <= '1' when ((re = '1' and hit = '0') or (we = '1' and(funct3 = F3_HALF or funct3 = F3_BYTE) and state = IDLE)) else '0';
    miss <= miss_int;

    -- Selección de salida: combinacional si hit, registrada si miss
    dout <= dout_comb when (re = '1' and hit = '1') else (others => '0');
    -- dout <= dout_comb when (re = '1' and hit = '1') else dout_reg;

    -- Read always a Word form RAM so the cache has all de bytes
    ram_funct3 <= F3_WORD when ram_re = '1' else funct3;

    -- Combinacional para lectura inmediata
    process(clk, reset, addr, din, we, re, funct3, byte_offset, data, index, ram_dout, miss)
        variable temp_byte : STD_LOGIC_VECTOR(7 downto 0);
        variable temp_half : STD_LOGIC_VECTOR(15 downto 0);
    begin
        dout_comb <= (others => '0');

        if re = '1' and hit = '1' then
            case funct3 is
                when F3_BYTE | F3_BYTE_U =>
                    case byte_offset is
                        when 0 => temp_byte := data(index)(7 downto 0);
                        when 1 => temp_byte := data(index)(15 downto 8);
                        when 2 => temp_byte := data(index)(23 downto 16);
                        when 3 => temp_byte := data(index)(31 downto 24);
                        when others => temp_byte := (others => '0');
                    end case;
                    if funct3 = F3_BYTE then
                        dout_comb <= (31 downto 8 => temp_byte(7)) & temp_byte;
                    else
                        dout_comb <= (31 downto 8 => '0') & temp_byte;
                    end if;

                when F3_HALF | F3_HALF_U =>
                    if byte_offset = 0 then
                        temp_half := data(index)(15 downto 0);
                    elsif byte_offset = 2 then
                        temp_half := data(index)(31 downto 16);
                    else
                        temp_half := (others => '0');
                    end if;
                    if funct3 = F3_HALF then
                        dout_comb <= (31 downto 16 => temp_half(15)) & temp_half;
                    else
                        dout_comb <= (31 downto 16 => '0') & temp_half;
                    end if;

                when F3_WORD =>
                    dout_comb <= data(index);

                when others =>
                    dout_comb <= data(index);
            end case;
        end if;
    end process;

    ram_we <= we when state = IDLE else '0';

    -- Memoria principal
    RAM_inst : RAM
        port map (
            clk    => clk,
            reset  => reset,
            we     => ram_we,
            re     => ram_re,
            addr   => addr,
            din    => din,
            funct3 => ram_funct3,
            dout   => ram_dout
        );

    -- Control principal de la caché
    process(clk)
        variable temp_word : STD_LOGIC_VECTOR(31 downto 0);
    begin
        if rising_edge(clk) then
            if reset = '1' then
                valid     <= (others => '0');
                ram_re    <= '0';
                state     <= IDLE;
               -- dout_reg  <= (others => '0');

            else
                case state is
                    when IDLE =>
                        ram_re <= '0';

                        if re = '1' and hit = '0' then
                            ram_re <= '1';
                            state  <= WAIT_READ;

                        elsif we = '1' then
                            temp_word := data(index);
                            case funct3 is
                                when F3_BYTE =>
                                    case byte_offset is
                                        when 0 => temp_word(7 downto 0) := din(7 downto 0);
                                        when 1 => temp_word(15 downto 8) := din(7 downto 0);
                                        when 2 => temp_word(23 downto 16) := din(7 downto 0);
                                        when 3 => temp_word(31 downto 24) := din(7 downto 0);
                                        when others => null;
                                    end case;
                                when F3_HALF =>
                                    if byte_offset = 0 then
                                        temp_word(15 downto 0) := din(15 downto 0);
                                    elsif byte_offset = 2 then
                                        temp_word(31 downto 16) := din(15 downto 0);
                                    end if;
                                when F3_WORD =>
                                    temp_word := din;
                                when others =>
                                    temp_word := din;
                            end case;

                            data(index)  <= temp_word;
                            tag(index)   <= addr_tag;
                            valid(index) <= '1';

                            if(funct3 = F3_BYTE or funct3 = F3_HALF)then
                                state  <= WRITE_HB;
                                ram_re <= '1';
                            else
                                state  <= IDLE;
                                ram_re <= '0';
                            end if;
                        end if;

                    when WAIT_READ =>
                        ram_re <= '0';
                        data(index)   <= ram_dout;
                        tag(index)    <= addr_tag;
                        valid(index)  <= '1';
                      --  dout_reg      <= ram_dout; -- capturamos valor para miss
                        state         <= IDLE;

                    when WRITE_HB =>
                        ram_re <= '0';
                        data(index)   <= ram_dout;
                        tag(index)    <= addr_tag;
                        valid(index)  <= '1';
                      --  dout_reg      <= ram_dout; -- capturamos valor para miss
                        state         <= IDLE;

                    when others =>
                        valid     <= (others => '0');
                        ram_re    <= '0';
                        state     <= IDLE; --
                       -- dout_reg  <= (others => '0');
                end case;
            end if;
        end if;
    end process;

end Behavioral;

tb/tb_cache_miss_2.vhd
library IEEE;
use IEEE.STD_LOGIC_1164.ALL;
use IEEE.NUMERIC_STD.ALL;

entity tb_cache_miss_2 is
end tb_cache_miss_2;

architecture Behavioral of tb_cache_miss_2 is
    -- Constants for RISC-V funct3
    constant F3_WORD      : STD_LOGIC_VECTOR(2 downto 0) := "010"; -- lw/sw
    constant F3_HALF      : STD_LOGIC_VECTOR(2 downto 0) := "001"; -- lh/sh
    constant F3_BYTE      : STD_LOGIC_VECTOR(2 downto 0) := "000"; -- lb/sb
    constant F3_HALF_U      : STD_LOGIC_VECTOR(2 downto 0) := "101"; -- lhu
    constant F3_BYTE_U      : STD_LOGIC_VECTOR(2 downto 0) := "100"; -- lbu

    -- Testbench signals
    signal clk      : STD_LOGIC := '0';
    signal reset    : STD_LOGIC := '0';
    signal addr     : STD_LOGIC_VECTOR(31 downto 0) := (others => '0');
    signal din      : STD_LOGIC_VECTOR(31 downto 0) := (others => '0');
    signal we       : STD_LOGIC := '0';
    signal re       : STD_LOGIC := '0';
    signal funct3   : STD_LOGIC_VECTOR(2 downto 0) := (others => '0');
    signal dout     : STD_LOGIC_VECTOR(31 downto 0);
    signal miss     : STD_LOGIC;
    
    -- Clock period
    constant CLK_PERIOD : time := 10 ns;
    
    -- Simulation control signal
    signal sim_done : boolean := false;
    
    -- Cache component declaration
    component Cache is
        generic (
            CACHE_SIZE : integer := 64  -- number of cache lines (power of 2)
        );
        Port (
            clk      : in  STD_LOGIC;
            reset    : in  STD_LOGIC;
            addr     : in  STD_LOGIC_VECTOR(31 downto 0);
            din      : in  STD_LOGIC_VECTOR(31 downto 0);
            we       : in  STD_LOGIC;
            re       : in  STD_LOGIC;
            funct3   : in  STD_LOGIC_VECTOR(2 downto 0);
            dout     : out STD_LOGIC_VECTOR(31 downto 0);
            miss     : out  STD_LOGIC
        );
    end component;

begin
    -- Cache instantiation with small size (16 lines)
    UUT: Cache
        generic map (
            CACHE_SIZE => 4  -- Small cache size
        )
        port map (
            clk     => clk,
            reset   => reset,
            addr    => addr,
            din     => din,
            we      => we,
            re      => re,
            funct3  => funct3,
            dout    => dout,
            miss    => miss
        );
    
    -- Clock generation process
    clock_process: process
    begin
        while not sim_done loop
            clk <= '0';
            wait for CLK_PERIOD/2;
            clk <= '1';
            wait for CLK_PERIOD/2;
        end loop;
        wait;
    end process;
    
    -- Stimulus process
    stimulus: process
        -- Procedure to wait n cycles
        procedure wait_cycles(n: integer) is
        begin
            for i in 1 to n loop
                wait until rising_edge(clk);
            end loop;
        end procedure;
        
        -- Procedure to write to memory
        procedure write_mem(
            address : in STD_LOGIC_VECTOR(31 downto 0);
            data    : in STD_LOGIC_VECTOR(31 downto 0);
            f3      : in STD_LOGIC_VECTOR(2 downto 0)
        ) is
        begin
            -- wait until rising_edge(clk);
            addr   <= address;
            din    <= data;
            funct3 <= f3;             -- uso del nuevo parámetro
            we     <= '1';
            re     <= '0';
            wait_cycles(1);
            -- we     <= '0';
            -- wait_cycles(1);
        end procedure;
        
        -- Procedure to read from memory
        procedure read_mem(
            address: in STD_LOGIC_VECTOR(31 downto 0);
            f3      : in STD_LOGIC_VECTOR(2 downto 0)
            ) is
        begin
            -- wait until rising_edge(clk);
            addr <= address;
            funct3 <= f3;
            re <= '1';
            we <= '0';
            wait_cycles(1);
            -- re <= '0';
            -- wait_cycles(1);
        end procedure;

        procedure down_sig is
        begin
            addr   <= (others => '0');
            din    <= (others => '0');
            funct3 <= (others => '0');             -- uso del nuevo parámetro
            we     <= '0';
            re     <= '0';
            wait_cycles(1);
        end procedure;
        
    begin
        -- Reset initial
        reset <= '1';
        wait_cycles(2);
        reset <= '0';
        wait until rising_edge(clk);
        
        report "TEST 1: Sequential Access (Fill Cache)";
        -- Write to sequential addresses to fill cache
        write_mem(x"00000100", x"18191A1B", F3_WORD);
        write_mem(x"00000104", x"28292A2B", F3_WORD);
        write_mem(x"00000108", x"38393A3B", F3_WORD);
        write_mem(x"0000010C", x"48494A4B", F3_WORD);
        
        -- Read back - these should be cache hits
        read_mem(x"00000100", F3_WORD);
        read_mem(x"00000104", F3_WORD);
        read_mem(x"00000108", F3_WORD);
        read_mem(x"0000010C", F3_WORD);

        down_sig;

        write_mem(x"00000110", x"58595A5B", F3_WORD);
        write_mem(x"00000114", x"68696A6B", F3_WORD);
        write_mem(x"00000118", x"78797A7B", F3_WORD);
        write_mem(x"0000011C", x"88898A8B", F3_WORD);

        read_mem(x"00000110", F3_WORD);
        read_mem(x"00000114", F3_WORD);

        down_sig;
        -- Cache miss
        read_mem(x"00000100", F3_WORD);
        wait_cycles(2);
        read_mem(x"00000114", F3_WORD);
        read_mem(x"00000118", F3_WORD);
        read_mem(x"00000100", F3_WORD);

        down_sig;
        wait_cycles(2);
        write_mem(x"00000104", x"E1E2E3E4", F3_HALF); 
        wait_cycles(1);
        write_mem(x"00000108", x"F1F2F3F4", F3_BYTE);
        wait_cycles(1);
        down_sig;
        read_mem(x"00000104", F3_WORD);
        read_mem(x"00000108", F3_WORD);
        read_mem(x"00000114", F3_HALF_U);
        wait_cycles(2);
        read_mem(x"00000114", F3_WORD);
        read_mem(x"00000118", F3_BYTE_U);
        wait_cycles(2);
        read_mem(x"00000118", F3_WORD);
        read_mem(x"00000104", F3_HALF);
        wait_cycles(2);
        read_mem(x"00000104", F3_WORD);
        read_mem(x"00000108", F3_BYTE);
        wait_cycles(2);
        read_mem(x"00000108", F3_WORD);
        down_sig;



        
        
        -- Test complete
        wait_cycles(2);
        sim_done <= true;
        wait;
    end process;

end Behavioral;

sim/tb_cache_miss_2/wave.vcd
$date
  Wed Apr 16 15:38:10 2025
$end
$version
  GHDL v0
$end
$timescale
  1 fs
$end
$scope module standard $end
$upscope $end
$scope module textio $end
$upscope $end
$scope module std_logic_1164 $end
$upscope $end
$scope module numeric_std $end
$upscope $end
$scope module math_real $end
$upscope $end
$scope module tb_cache_miss_2 $end
$var reg 1 ! clk $end
$var reg 1 " reset $end
$var reg 32 # addr[31:0] $end
$var reg 32 $ din[31:0] $end
$var reg 1 % we $end
$var reg 1 & re $end
$var reg 3 ' funct3[2:0] $end
$var reg 32 ( dout[31:0] $end
$var reg 1 ) miss $end
$var reg 1 * sim_done $end
$scope module uut $end
$var reg 1 + clk $end
$var reg 1 , reset $end
$var reg 32 - addr[31:0] $end
$var reg 32 . din[31:0] $end
$var reg 1 / we $end
$var reg 1 0 re $end
$var reg 3 1 funct3[2:0] $end
$var reg 32 2 dout[31:0] $end
$var reg 1 3 miss $end
$comment data is not handled $end
$comment tag is not handled $end
$var reg 4 4 valid[0:3] $end
$var integer 32 5 index $end
$var reg 28 6 addr_tag[27:0] $end
$var reg 1 7 hit $end
$var integer 32 8 byte_offset $end
$var reg 1 9 ram_re $end
$var reg 32 : ram_dout[31:0] $end
$var reg 3 ; ram_funct3[2:0] $end
$var reg 32 < dout_comb[31:0] $end
$var reg 1 = miss_int $end
$var reg 1 > ram_we $end
$var reg 2 ? state[1:0] $end
$scope module ram_inst $end
$var reg 1 @ clk $end
$var reg 1 A reset $end
$var reg 1 B we $end
$var reg 1 C re $end
$var reg 32 D addr[31:0] $end
$var reg 32 E din[31:0] $end
$var reg 3 F funct3[2:0] $end
$var reg 32 G dout[31:0] $end
$comment memory is not handled $end
$var integer 32 H aligned_addr $end
$var reg 32 I dout_aux[31:0] $end
$upscope $end
$upscope $end
$upscope $end
$enddefinitions $end
#0
0!
1"
b00000000000000000000000000000000 #
b00000000000000000000000000000000 $
0%
0&
b000 '
b00000000000000000000000000000000 (
0)
0*
0+
1,
b00000000000000000000000000000000 -
b00000000000000000000000000000000 .
0/
00
b000 1
b00000000000000000000000000000000 2
03
b0000 4
b0 5
b0000000000000000000000000000 6
07
b0 8
09
b00000000000000000000000000000000 :
b000 ;
b00000000000000000000000000000000 <
0=
0>
b00 ?
0@
1A
0B
0C
b00000000000000000000000000000000 D
b00000000000000000000000000000000 E
b000 F
b00000000000000000000000000000000 G
b0 H
b00000000000000000000000000000000 I
#5000000
1!
1+
1@
#10000000
0!
0+
0@
#15000000
1!
0"
1+
0,
1@
0A
#20000000
0!
0+
0@
#25000000
1!
b00000000000000000000000100000000 #
b00011000000110010001101000011011 $
1%
b010 '
1+
b00000000000000000000000100000000 -
b00011000000110010001101000011011 .
1/
b010 1
b0000000000000000000000010000 6
b010 ;
1>
1@
1B
b00000000000000000000000100000000 D
b00011000000110010001101000011011 E
b010 F
b100000000 H
#30000000
0!
0+
0@
#35000000
1!
b00000000000000000000000100000100 #
b00101000001010010010101000101011 $
1+
b00000000000000000000000100000100 -
b00101000001010010010101000101011 .
b1000 4
b1 5
07
1@
b00000000000000000000000100000100 D
b00101000001010010010101000101011 E
b100000100 H
#40000000
0!
0+
0@
#45000000
1!
b00000000000000000000000100001000 #
b00111000001110010011101000111011 $
1+
b00000000000000000000000100001000 -
b00111000001110010011101000111011 .
b1100 4
b10 5
07
1@
b00000000000000000000000100001000 D
b00111000001110010011101000111011 E
b100001000 H
#50000000
0!
0+
0@
#55000000
1!
b00000000000000000000000100001100 #
b01001000010010010100101001001011 $
1+
b00000000000000000000000100001100 -
b01001000010010010100101001001011 .
b1110 4
b11 5
07
1@
b00000000000000000000000100001100 D
b01001000010010010100101001001011 E
b100001100 H
#60000000
0!
0+
0@
#65000000
1!
b00000000000000000000000100000000 #
0%
1&
b00011000000110010001101000011011 (
0)
1+
b00000000000000000000000100000000 -
0/
10
b00011000000110010001101000011011 2
03
b1111 4
b0 5
17
b00011000000110010001101000011011 <
0=
0>
1@
0B
b00000000000000000000000100000000 D
b100000000 H
b00011000000110010001101000011011 I
#70000000
0!
0+
0@
#75000000
1!
b00000000000000000000000100000100 #
b00101000001010010010101000101011 (
1+
b00000000000000000000000100000100 -
b00101000001010010010101000101011 2
b1 5
b00101000001010010010101000101011 <
1@
b00000000000000000000000100000100 D
b100000100 H
b00101000001010010010101000101011 I
#80000000
0!
0+
0@
#85000000
1!
b00000000000000000000000100001000 #
b00111000001110010011101000111011 (
1+
b00000000000000000000000100001000 -
b00111000001110010011101000111011 2
b10 5
b00111000001110010011101000111011 <
1@
b00000000000000000000000100001000 D
b100001000 H
b00111000001110010011101000111011 I
#90000000
0!
0+
0@
#95000000
1!
b00000000000000000000000100001100 #
b01001000010010010100101001001011 (
1+
b00000000000000000000000100001100 -
b01001000010010010100101001001011 2
b11 5
b01001000010010010100101001001011 <
1@
b00000000000000000000000100001100 D
b100001100 H
b01001000010010010100101001001011 I
#100000000
0!
0+
0@
#105000000
1!
b00000000000000000000000000000000 #
b00000000000000000000000000000000 $
0&
b000 '
b00000000000000000000000000000000 (
1+
b00000000000000000000000000000000 -
b00000000000000000000000000000000 .
00
b000 1
b00000000000000000000000000000000 2
b0 5
b0000000000000000000000000000 6
07
b000 ;
b00000000000000000000000000000000 <
1@
b00000000000000000000000000000000 D
b00000000000000000000000000000000 E
b000 F
b0 H
b00000000000000000000000000000000 I
#110000000
0!
0+
0@
#115000000
1!
b00000000000000000000000100010000 #
b01011000010110010101101001011011 $
1%
b010 '
1+
b00000000000000000000000100010000 -
b01011000010110010101101001011011 .
1/
b010 1
b0000000000000000000000010001 6
b010 ;
1>
1@
1B
b00000000000000000000000100010000 D
b01011000010110010101101001011011 E
b010 F
b100010000 H
#120000000
0!
0+
0@
#125000000
1!
b00000000000000000000000100010100 #
b01101000011010010110101001101011 $
1+
b00000000000000000000000100010100 -
b01101000011010010110101001101011 .
b1 5
07
1@
b00000000000000000000000100010100 D
b01101000011010010110101001101011 E
b100010100 H
#130000000
0!
0+
0@
#135000000
1!
b00000000000000000000000100011000 #
b01111000011110010111101001111011 $
1+
b00000000000000000000000100011000 -
b01111000011110010111101001111011 .
b10 5
07
1@
b00000000000000000000000100011000 D
b01111000011110010111101001111011 E
b100011000 H
#140000000
0!
0+
0@
#145000000
1!
b00000000000000000000000100011100 #
b10001000100010011000101010001011 $
1+
b00000000000000000000000100011100 -
b10001000100010011000101010001011 .
b11 5
07
1@
b00000000000000000000000100011100 D
b10001000100010011000101010001011 E
b100011100 H
#150000000
0!
0+
0@
#155000000
1!
b00000000000000000000000100010000 #
0%
1&
b01011000010110010101101001011011 (
0)
1+
b00000000000000000000000100010000 -
0/
10
b01011000010110010101101001011011 2
03
b0 5
17
b01011000010110010101101001011011 <
0=
0>
1@
0B
b00000000000000000000000100010000 D
b100010000 H
b01011000010110010101101001011011 I
#160000000
0!
0+
0@
#165000000
1!
b00000000000000000000000100010100 #
b01101000011010010110101001101011 (
1+
b00000000000000000000000100010100 -
b01101000011010010110101001101011 2
b1 5
b01101000011010010110101001101011 <
1@
b00000000000000000000000100010100 D
b100010100 H
b01101000011010010110101001101011 I
#170000000
0!
0+
0@
#175000000
1!
b00000000000000000000000000000000 #
b00000000000000000000000000000000 $
0&
b000 '
b00000000000000000000000000000000 (
1+
b00000000000000000000000000000000 -
b00000000000000000000000000000000 .
00
b000 1
b00000000000000000000000000000000 2
b0 5
b0000000000000000000000000000 6
07
b000 ;
b00000000000000000000000000000000 <
1@
b00000000000000000000000000000000 D
b00000000000000000000000000000000 E
b000 F
b0 H
b00000000000000000000000000000000 I
#180000000
0!
0+
0@
#185000000
1!
b00000000000000000000000100000000 #
1&
b010 '
1)
1+
b00000000000000000000000100000000 -
10
b010 1
13
b0000000000000000000000010000 6
b010 ;
1=
1@
b00000000000000000000000100000000 D
b010 F
b100000000 H
b00011000000110010001101000011011 I
#190000000
0!
0+
0@
#195000000
1!
1+
19
b00011000000110010001101000011011 :
b01 ?
1@
1C
b00011000000110010001101000011011 G
#200000000
0!
0+
0@
#205000000
1!
b00011000000110010001101000011011 (
0)
1+
b00011000000110010001101000011011 2
03
17
09
b00000000000000000000000000000000 :
b00011000000110010001101000011011 <
0=
b00 ?
1@
0C
b00000000000000000000000000000000 G
#210000000
0!
0+
0@
#215000000
1!
b00000000000000000000000100010100 #
b01101000011010010110101001101011 (
1+
b00000000000000000000000100010100 -
b01101000011010010110101001101011 2
b1 5
b0000000000000000000000010001 6
b01101000011010010110101001101011 <
1@
b00000000000000000000000100010100 D
b100010100 H
b01101000011010010110101001101011 I
#220000000
0!
0+
0@
#225000000
1!
b00000000000000000000000100011000 #
b01111000011110010111101001111011 (
1+
b00000000000000000000000100011000 -
b01111000011110010111101001111011 2
b10 5
b01111000011110010111101001111011 <
1@
b00000000000000000000000100011000 D
b100011000 H
b01111000011110010111101001111011 I
#230000000
0!
0+
0@
#235000000
1!
b00000000000000000000000100000000 #
b00011000000110010001101000011011 (
1+
b00000000000000000000000100000000 -
b00011000000110010001101000011011 2
b0 5
b0000000000000000000000010000 6
b00011000000110010001101000011011 <
1@
b00000000000000000000000100000000 D
b100000000 H
b00011000000110010001101000011011 I
#240000000
0!
0+
0@
#245000000
1!
b00000000000000000000000000000000 #
0&
b000 '
b00000000000000000000000000000000 (
1+
b00000000000000000000000000000000 -
00
b000 1
b00000000000000000000000000000000 2
b0000000000000000000000000000 6
07
b000 ;
b00000000000000000000000000000000 <
1@
b00000000000000000000000000000000 D
b000 F
b0 H
b00000000000000000000000000000000 I
#250000000
0!
0+
0@
#255000000
1!
1+
1@
#260000000
0!
0+
0@
#265000000
1!
1+
1@
#270000000
0!
0+
0@
#275000000
1!
b00000000000000000000000100000100 #
b11100001111000101110001111100100 $
1%
b001 '
1)
1+
b00000000000000000000000100000100 -
b11100001111000101110001111100100 .
1/
b001 1
13
b1 5
b0000000000000000000000010000 6
b001 ;
1=
1>
1@
1B
b00000000000000000000000100000100 D
b11100001111000101110001111100100 E
b001 F
b100000100 H
b00000000000000000010101000101011 I
#280000000
0!
0+
0@
#285000000
1!
0)
1+
03
17
19
b00101000001010011110001111100100 :
b010 ;
0=
0>
b10 ?
1@
0B
1C
b010 F
b00101000001010011110001111100100 G
b00101000001010011110001111100100 I
#290000000
0!
0+
0@
#295000000
1!
b00000000000000000000000100001000 #
b11110001111100101111001111110100 $
b000 '
1)
1+
b00000000000000000000000100001000 -
b11110001111100101111001111110100 .
b000 1
13
b10 5
07
09
b00000000000000000000000000000000 :
b000 ;
1=
1>
b00 ?
1@
1B
0C
b00000000000000000000000100001000 D
b11110001111100101111001111110100 E
b000 F
b00000000000000000000000000000000 G
b100001000 H
b11111111111111111111111100111011 I
#300000000
0!
0+
0@
#305000000
1!
0)
1+
03
17
19
b00111000001110010011101011110100 :
b010 ;
0=
0>
b10 ?
1@
0B
1C
b010 F
b00111000001110010011101011110100 G
b00111000001110010011101011110100 I
#310000000
0!
0+
0@
#315000000
1!
b00000000000000000000000000000000 #
b00000000000000000000000000000000 $
0%
1+
b00000000000000000000000000000000 -
b00000000000000000000000000000000 .
0/
b0 5
b0000000000000000000000000000 6
07
09
b00000000000000000000000000000000 :
b000 ;
b00 ?
1@
0C
b00000000000000000000000000000000 D
b00000000000000000000000000000000 E
b000 F
b00000000000000000000000000000000 G
b0 H
b11111111111111111111111100000000 I
#320000000
0!
0+
0@
#325000000
1!
b00000000000000000000000100000100 #
1&
b010 '
b00101000001010011110001111100100 (
0)
1+
b00000000000000000000000100000100 -
10
b010 1
b00101000001010011110001111100100 2
03
b1 5
b0000000000000000000000010000 6
17
b010 ;
b00101000001010011110001111100100 <
0=
1@
b00000000000000000000000100000100 D
b010 F
b100000100 H
b00101000001010011110001111100100 I
#330000000
0!
0+
0@
#335000000
1!
b00000000000000000000000100001000 #
b00111000001110010011101011110100 (
1+
b00000000000000000000000100001000 -
b00111000001110010011101011110100 2
b10 5
b00111000001110010011101011110100 <
1@
b00000000000000000000000100001000 D
b100001000 H
b00111000001110010011101011110100 I
#340000000
0!
0+
0@
#345000000
1!
b00000000000000000000000100010100 #
b001 '
b00000000000000000000000000000000 (
1)
1+
b00000000000000000000000100010100 -
b001 1
b00000000000000000000000000000000 2
13
b1 5
b0000000000000000000000010001 6
07
b001 ;
b00000000000000000000000000000000 <
1=
1@
b00000000000000000000000100010100 D
b001 F
b100010100 H
b00000000000000000110101001101011 I
#350000000
0!
0+
0@
#355000000
1!
1+
19
b01101000011010010110101001101011 :
b010 ;
b01 ?
1@
1C
b010 F
b01101000011010010110101001101011 G
b01101000011010010110101001101011 I
#360000000
0!
0+
0@
#365000000
1!
b00000000000000000110101001101011 (
0)
1+
b00000000000000000110101001101011 2
03
17
09
b00000000000000000000000000000000 :
b001 ;
b00000000000000000110101001101011 <
0=
b00 ?
1@
0C
b001 F
b00000000000000000000000000000000 G
b00000000000000000110101001101011 I
#370000000
0!
0+
0@
#375000000
1!
b010 '
b01101000011010010110101001101011 (
1+
b010 1
b01101000011010010110101001101011 2
b010 ;
b01101000011010010110101001101011 <
1@
b010 F
b01101000011010010110101001101011 I
#380000000
0!
0+
0@
