src/PC.vhd
library IEEE;
use IEEE.STD_LOGIC_1164.ALL;
use IEEE.STD_LOGIC_UNSIGNED.ALL;
use IEEE.NUMERIC_STD.ALL;


entity PC is
    Port (
        clk         : in  STD_LOGIC;
        reset       : in  STD_LOGIC;
        branch      : in  STD_LOGIC;
        -- stall       : in  STD_LOGIC;
        ImmExt      : in  STD_LOGIC_VECTOR (31 downto 0);
        PC_out      : out STD_LOGIC_VECTOR (31 downto 0)
    );
end PC;

architecture Behavioral of PC is
    signal PC_reg      : STD_LOGIC_VECTOR (31 downto 0) := (others => '0'); -- Registro del valor actual del PC
    signal PC_Next     : STD_LOGIC_VECTOR (31 downto 0);                    -- Valor siguiente del PC 
    signal PC_Plus4    : STD_LOGIC_VECTOR (31 downto 0);                    -- PC + 4, dirección de la siguiente instrucción en ejecución
begin
    -- Lógica combinacional para PC_Plus4
    PC_Plus4  <= PC_reg + 4;
    PC_Next <= ImmExt when branch = '1' else (others => '0') when reset = '1' else PC_Plus4;        -- MUX para seleccionar PC_Next

    -- Proceso para actualizar el registro del PC
    process(clk, reset)
    begin
        if rising_edge(clk) then
            if reset = '1' then
                PC_reg <= (others => '0');         -- Reset síncrono: inicializa el PC a 0
            else
                PC_reg <= PC_Next;             -- Actualiza el PC con PC_Next
            end if;
        end if;
    end process;
    PC_out <= PC_reg;                           -- Asignar el valor del registro PC a la salida
end Behavioral;

tb/tb_PC.vhd
library IEEE;
use IEEE.STD_LOGIC_1164.ALL;
use IEEE.STD_LOGIC_UNSIGNED.ALL;
use IEEE.NUMERIC_STD.ALL;

entity tb_PC is
end tb_PC;

architecture test of tb_PC is
    signal clk      : std_logic := '0';
    signal reset    : std_logic := '0';
    signal branch   : std_logic := '0';
    signal ImmExt   : std_logic_vector(31 downto 0) := (others => '0');
    signal PC_out   : std_logic_vector(31 downto 0);

    constant CLK_PERIOD : time := 10 ns;

begin
    uut: entity work.PC
        port map (
            clk     => clk,
            reset   => reset,
            branch  => branch,
            ImmExt  => ImmExt,
            PC_out  => PC_out
        );

    -- Generador de reloj
    process
    constant SIM_TIME : time := 200 ns;
    begin
        while now < SIM_TIME loop 
            clk <= '1';
            wait for CLK_PERIOD / 2;
            clk <= '0';
            wait for CLK_PERIOD / 2;
        end loop;
        wait; 
    end process;

    -- Estímulos para probar el diseño
    process
    begin
        -- 1. Reset activo (PC debe inicializarse en 0)
        reset <= '1';
        wait for CLK_PERIOD;
        reset <= '0';
        wait for CLK_PERIOD;
        
        -- 2. Normal operation (PC avanza en +4)
        wait for 2*CLK_PERIOD;

        -- 3. Activa branch (PC cambia a ImmExt)
        branch <= '1';
        ImmExt <= X"00000020";  -- PC debe cambiar a 32
        wait for CLK_PERIOD;
        
        -- 4. Desactiva branch (PC debe volver a avanzar de 4 en 4)
        branch <= '0';
        wait for 2* CLK_PERIOD;

        -- 5. Vuelve a activar reset
        reset <= '1';
        wait for CLK_PERIOD;
        reset <= '0';
        wait for CLK_PERIOD;

        wait; -- Termina el proceso
    end process;
end test;

sim/tb_PC/wave.vcd
$date
  Sun Mar  2 16:34:45 2025
$end
$version
  GHDL v0
$end
$timescale
  1 fs
$end
$scope module standard $end
$upscope $end
$scope module textio $end
$upscope $end
$scope module std_logic_1164 $end
$upscope $end
$scope module std_logic_arith $end
$upscope $end
$scope module std_logic_unsigned $end
$upscope $end
$scope module numeric_std $end
$upscope $end
$scope module tb_pc $end
$var reg 1 ! clk $end
$var reg 1 " reset $end
$var reg 1 # branch $end
$var reg 32 $ immext[31:0] $end
$var reg 32 % pc_out[31:0] $end
$scope module uut $end
$var reg 1 & clk $end
$var reg 1 ' reset $end
$var reg 1 ( branch $end
$var reg 32 ) immext[31:0] $end
$var reg 32 * pc_out[31:0] $end
$var reg 32 + pc_reg[31:0] $end
$var reg 32 , pc_next[31:0] $end
$var reg 32 - pc_plus4[31:0] $end
$upscope $end
$upscope $end
$enddefinitions $end
#0
1!
1"
0#
b00000000000000000000000000000000 $
b00000000000000000000000000000000 %
1&
1'
0(
b00000000000000000000000000000000 )
b00000000000000000000000000000000 *
b00000000000000000000000000000000 +
b00000000000000000000000000000000 ,
b00000000000000000000000000000100 -
#5000000
0!
0&
#10000000
1!
0"
1&
0'
b00000000000000000000000000000100 ,
#15000000
0!
0&
#20000000
1!
b00000000000000000000000000000100 %
1&
b00000000000000000000000000000100 *
b00000000000000000000000000000100 +
b00000000000000000000000000001000 ,
b00000000000000000000000000001000 -
#25000000
0!
0&
#30000000
1!
b00000000000000000000000000001000 %
1&
b00000000000000000000000000001000 *
b00000000000000000000000000001000 +
b00000000000000000000000000001100 ,
b00000000000000000000000000001100 -
#35000000
0!
0&
#40000000
1!
1#
b00000000000000000000000000100000 $
b00000000000000000000000000001100 %
1&
1(
b00000000000000000000000000100000 )
b00000000000000000000000000001100 *
b00000000000000000000000000001100 +
b00000000000000000000000000100000 ,
b00000000000000000000000000010000 -
#45000000
0!
0&
#50000000
1!
0#
b00000000000000000000000000100000 %
1&
0(
b00000000000000000000000000100000 *
b00000000000000000000000000100000 +
b00000000000000000000000000100100 ,
b00000000000000000000000000100100 -
#55000000
0!
0&
#60000000
1!
b00000000000000000000000000100100 %
1&
b00000000000000000000000000100100 *
b00000000000000000000000000100100 +
b00000000000000000000000000101000 ,
b00000000000000000000000000101000 -
#65000000
0!
0&
#70000000
1!
1"
b00000000000000000000000000000000 %
1&
1'
b00000000000000000000000000000000 *
b00000000000000000000000000000000 +
b00000000000000000000000000000000 ,
b00000000000000000000000000000100 -
#75000000
0!
0&
#80000000
1!
0"
1&
0'
b00000000000000000000000000000100 ,
#85000000
0!
0&
#90000000
1!
b00000000000000000000000000000100 %
1&
b00000000000000000000000000000100 *
b00000000000000000000000000000100 +
b00000000000000000000000000001000 ,
b00000000000000000000000000001000 -
#95000000
0!
0&
#100000000
1!
b00000000000000000000000000001000 %
1&
b00000000000000000000000000001000 *
b00000000000000000000000000001000 +
b00000000000000000000000000001100 ,
b00000000000000000000000000001100 -
#105000000
0!
0&
#110000000
1!
b00000000000000000000000000001100 %
1&
b00000000000000000000000000001100 *
b00000000000000000000000000001100 +
b00000000000000000000000000010000 ,
b00000000000000000000000000010000 -
#115000000
0!
0&
#120000000
1!
b00000000000000000000000000010000 %
1&
b00000000000000000000000000010000 *
b00000000000000000000000000010000 +
b00000000000000000000000000010100 ,
b00000000000000000000000000010100 -
#125000000
0!
0&
#130000000
1!
b00000000000000000000000000010100 %
1&
b00000000000000000000000000010100 *
b00000000000000000000000000010100 +
b00000000000000000000000000011000 ,
b00000000000000000000000000011000 -
#135000000
0!
0&
#140000000
1!
b00000000000000000000000000011000 %
1&
b00000000000000000000000000011000 *
b00000000000000000000000000011000 +
b00000000000000000000000000011100 ,
b00000000000000000000000000011100 -
#145000000
0!
0&
#150000000
1!
b00000000000000000000000000011100 %
1&
b00000000000000000000000000011100 *
b00000000000000000000000000011100 +
b00000000000000000000000000100000 ,
b00000000000000000000000000100000 -
#155000000
0!
0&
#160000000
1!
b00000000000000000000000000100000 %
1&
b00000000000000000000000000100000 *
b00000000000000000000000000100000 +
b00000000000000000000000000100100 ,
b00000000000000000000000000100100 -
#165000000
0!
0&
#170000000
1!
b00000000000000000000000000100100 %
1&
b00000000000000000000000000100100 *
b00000000000000000000000000100100 +
b00000000000000000000000000101000 ,
b00000000000000000000000000101000 -
#175000000
0!
0&
#180000000
1!
b00000000000000000000000000101000 %
1&
b00000000000000000000000000101000 *
b00000000000000000000000000101000 +
b00000000000000000000000000101100 ,
b00000000000000000000000000101100 -
#185000000
0!
0&
#190000000
1!
b00000000000000000000000000101100 %
1&
b00000000000000000000000000101100 *
b00000000000000000000000000101100 +
b00000000000000000000000000110000 ,
b00000000000000000000000000110000 -
