src/RegFile.vhd
library IEEE;
use IEEE.STD_LOGIC_1164.ALL;
use IEEE.NUMERIC_STD.ALL;

entity RegFile is
    Port (
        clk             : in  STD_LOGIC;
        reset           : in  STD_LOGIC;
        Read_Reg1       : in  STD_LOGIC_VECTOR (4 downto 0);
        Read_Reg2       : in  STD_LOGIC_VECTOR (4 downto 0);
        Write_Reg       : in  STD_LOGIC_VECTOR (4 downto 0);
        Write_Data      : in  STD_LOGIC_VECTOR (31 downto 0);
        Write_Enable    : in  STD_LOGIC;
        Read_Data1      : out STD_LOGIC_VECTOR (31 downto 0);
        Read_Data2      : out STD_LOGIC_VECTOR (31 downto 0)
    );
end RegFile;

architecture Behavioral of RegFile is
    type Reg_Array is array (0 to 31) of STD_LOGIC_VECTOR(31 downto 0);
    signal RF : Reg_Array := (others => (others => '0'));
begin
    -- LECTURA EN FLANCO BAJO DEL RELOJ
    process(clk)
    begin
        if falling_edge(clk) then
            if Read_Reg1 = "00000" then
                Read_Data1 <= (others => '0'); -- Registro 0 siempre es 0
            else
                Read_Data1 <= RF(to_integer(unsigned(Read_Reg1)));
            end if;

            if Read_Reg2 = "00000" then
                Read_Data2 <= (others => '0'); -- Registro 0 siempre es 0
            else
                Read_Data2 <= RF(to_integer(unsigned(Read_Reg2)));
            end if;
        end if;
    end process;

    -- ESCRITURA EN FLANCO ALTO DEL RELOJ
    process(clk)
    begin
        if rising_edge(clk) then
            if reset = '1' then
                RF <= (others => (others => '0')); -- Reset síncrono
            elsif (Write_Enable = '1' and Write_Reg /= "00000") then
                RF(to_integer(unsigned(Write_Reg))) <= Write_Data;
            end if;
        end if;
    end process;
end Behavioral;

tb/tb_RegFile.vhd
library IEEE;
use IEEE.STD_LOGIC_1164.ALL;
use IEEE.NUMERIC_STD.ALL;

entity tb_RegFile is
end tb_RegFile;

architecture test of tb_RegFile is
    signal clk          : STD_LOGIC := '0';
    signal reset        : STD_LOGIC := '0';
    signal Read_Reg1    : STD_LOGIC_VECTOR (4 downto 0) := "00000";
    signal Read_Reg2    : STD_LOGIC_VECTOR (4 downto 0) := "00000";
    signal Write_Reg    : STD_LOGIC_VECTOR (4 downto 0) := "00000";
    signal Write_Data   : STD_LOGIC_VECTOR (31 downto 0) := (others => '0');
    signal Write_Enable : STD_LOGIC := '0';
    signal Read_Data1   : STD_LOGIC_VECTOR (31 downto 0);
    signal Read_Data2   : STD_LOGIC_VECTOR (31 downto 0);

    constant clk_period : time := 10 ns;

begin
    -- Instancia del DUT (Dispositivo Bajo Prueba)
    uut: entity work.RegFile
        port map (
            clk          => clk,
            reset        => reset,
            Read_Reg1    => Read_Reg1,
            Read_Reg2    => Read_Reg2,
            Write_Reg    => Write_Reg,
            Write_Data   => Write_Data,
            Write_Enable => Write_Enable,
            Read_Data1   => Read_Data1,
            Read_Data2   => Read_Data2
        );

    -- Generación del reloj
    process
    begin
        while now < 200 ns loop
            clk <= '0';
            wait for clk_period / 2;
            clk <= '1';
            wait for clk_period / 2;
        end loop;
        wait;
    end process;

    -- Proceso de prueba
    process
    begin
        -- RESET
        reset <= '1';
        wait for clk_period;
        reset <= '0';
        wait for clk_period;

        -- ESCRITURA EN R1 Y R2 (Debe ocurrir en flanco de subida)
        Write_Enable <= '1';

        Write_Reg  <= "00001"; -- R1
        Write_Data <= X"000000AA";
        wait for clk_period;

        Write_Reg  <= "00010"; -- R2
        Write_Data <= X"000000BB";
        wait for clk_period;

        -- INTENTAR ESCRIBIR EN R0 (Debe ignorarse)
        Write_Reg  <= "00000";
        Write_Data <= X"FFFFFFFF";
        wait for clk_period;

        -- DESHABILITAR ESCRITURA
        Write_Enable <= '0';

        -- LEER R1 Y R2 EN FLANCO BAJO
        wait for clk_period / 2;
        Read_Reg1 <= "00001"; -- R1
        Read_Reg2 <= "00010"; -- R2
        wait for clk_period / 2;

        Write_Enable <= '1';
        Write_Reg  <= "00001";
        Write_Data <= X"12FF2F0F";

        -- PRUEBA DE hAZARD

        -- LEER R1 Y R2 EN FLANCO BAJO
        wait for clk_period / 2;
        Read_Reg1 <= "00001"; -- R1
        Read_Reg2 <= "00010"; -- R2
        wait for  clk_period / 2;

        Write_Reg  <= "00001";
        Write_Data <= X"12FF2F0F";
        wait for  clk_period/2;

        Write_Reg  <= "00010";
        Write_Data <= X"00000012";
        wait for  clk_period;

        Write_Reg  <= "00010";
        Write_Data <= X"00000051";
        wait for  clk_period;

        Write_Reg  <= "00010";
        Write_Data <= X"000000a2";
        wait for  clk_period;

        Write_Enable <= '0';



        -- LEER R0 (Debe devolver 0)
        wait for clk_period / 2;
        Read_Reg1 <= "00000";
        Read_Reg2 <= "00000";
        wait for clk_period / 2;

        -- FIN DE LA SIMULACIÓN
        wait;
    end process;

end test;

sim/tb_RegFile/wave.vcd
$date
  Mon Mar  3 21:35:48 2025
$end
$version
  GHDL v0
$end
$timescale
  1 fs
$end
$scope module standard $end
$upscope $end
$scope module textio $end
$upscope $end
$scope module std_logic_1164 $end
$upscope $end
$scope module numeric_std $end
$upscope $end
$scope module tb_regfile $end
$var reg 1 ! clk $end
$var reg 1 " reset $end
$var reg 5 # read_reg1[4:0] $end
$var reg 5 $ read_reg2[4:0] $end
$var reg 5 % write_reg[4:0] $end
$var reg 32 & write_data[31:0] $end
$var reg 1 ' write_enable $end
$var reg 32 ( read_data1[31:0] $end
$var reg 32 ) read_data2[31:0] $end
$scope module uut $end
$var reg 1 * clk $end
$var reg 1 + reset $end
$var reg 5 , read_reg1[4:0] $end
$var reg 5 - read_reg2[4:0] $end
$var reg 5 . write_reg[4:0] $end
$var reg 32 / write_data[31:0] $end
$var reg 1 0 write_enable $end
$var reg 32 1 read_data1[31:0] $end
$var reg 32 2 read_data2[31:0] $end
$comment rf is not handled $end
$upscope $end
$upscope $end
$enddefinitions $end
#0
0!
1"
b00000 #
b00000 $
b00000 %
b00000000000000000000000000000000 &
0'
bUUUUUUUUUUUUUUUUUUUUUUUUUUUUUUUU (
bUUUUUUUUUUUUUUUUUUUUUUUUUUUUUUUU )
0*
1+
b00000 ,
b00000 -
b00000 .
b00000000000000000000000000000000 /
00
bUUUUUUUUUUUUUUUUUUUUUUUUUUUUUUUU 1
bUUUUUUUUUUUUUUUUUUUUUUUUUUUUUUUU 2
#5000000
1!
1*
#10000000
0!
0"
b00000000000000000000000000000000 (
b00000000000000000000000000000000 )
0*
0+
b00000000000000000000000000000000 1
b00000000000000000000000000000000 2
#15000000
1!
1*
#20000000
0!
b00001 %
b00000000000000000000000010101010 &
1'
0*
b00001 .
b00000000000000000000000010101010 /
10
#25000000
1!
1*
#30000000
0!
b00010 %
b00000000000000000000000010111011 &
0*
b00010 .
b00000000000000000000000010111011 /
#35000000
1!
1*
#40000000
0!
b00000 %
b11111111111111111111111111111111 &
0*
b00000 .
b11111111111111111111111111111111 /
#45000000
1!
1*
#50000000
0!
0'
0*
00
#55000000
1!
b00001 #
b00010 $
1*
b00001 ,
b00010 -
#60000000
0!
b00001 %
b00010010111111110010111100001111 &
1'
b00000000000000000000000010101010 (
b00000000000000000000000010111011 )
0*
b00001 .
b00010010111111110010111100001111 /
10
b00000000000000000000000010101010 1
b00000000000000000000000010111011 2
#65000000
1!
1*
#70000000
0!
b00010010111111110010111100001111 (
0*
b00010010111111110010111100001111 1
#75000000
1!
b00010 %
b00000000000000000000000000010010 &
1*
b00010 .
b00000000000000000000000000010010 /
#80000000
0!
b00000000000000000000000000010010 )
0*
b00000000000000000000000000010010 2
#85000000
1!
b00000000000000000000000001010001 &
1*
b00000000000000000000000001010001 /
#90000000
0!
b00000000000000000000000001010001 )
0*
b00000000000000000000000001010001 2
#95000000
1!
b00000000000000000000000010100010 &
1*
b00000000000000000000000010100010 /
#100000000
0!
b00000000000000000000000010100010 )
0*
b00000000000000000000000010100010 2
#105000000
1!
0'
1*
00
#110000000
0!
b00000 #
b00000 $
b00000000000000000000000000000000 (
b00000000000000000000000000000000 )
0*
b00000 ,
b00000 -
b00000000000000000000000000000000 1
b00000000000000000000000000000000 2
